voronoi_mapper/__init__.py
voronoi_mapper/geojson.py
voronoi_mapper/geometry.py
voronoi_mapper/models.py
voronoi_mapper/plot.py
voronoi_mapper/voronoi.py
voronoi_mapper-0.1.0.dist-info/METADATA
voronoi_mapper-0.1.0.dist-info/WHEEL
voronoi_mapper-0.1.0.dist-info/RECORD
