Metadata-Version: 2.1
Name: voronoi-mapper
Version: 0.1.0
Summary: 
Author: James Walden
Author-email: james.m.walden@outlook.com
Requires-Python: >=3.10,<4.0
Classifier: Programming Language :: Python :: 3
Classifier: Programming Language :: Python :: 3.10
Classifier: Programming Language :: Python :: 3.11
Requires-Dist: geopandas (>=0.14.3,<0.15.0)
Requires-Dist: matplotlib (>=3.8.4,<4.0.0)
Requires-Dist: numpy (>=1.26.4,<2.0.0)
Requires-Dist: scipy (>=1.13.0,<2.0.0)
Requires-Dist: shapely (>=2.0.4,<3.0.0)
